qgispluginreleaser/__init__.py
qgispluginreleaser/entry_point.py
qgispluginreleaser/test_entry_point.py
qgispluginreleaser/test_installation.py
qgispluginreleaser-2.0.2.dist-info/licenses/LICENSE.rst
qgispluginreleaser-2.0.2.dist-info/METADATA
qgispluginreleaser-2.0.2.dist-info/WHEEL
qgispluginreleaser-2.0.2.dist-info/entry_points.txt
qgispluginreleaser-2.0.2.dist-info/top_level.txt
qgispluginreleaser-2.0.2.dist-info/RECORD
