Metadata-Version: 2.4
Name: qgispluginreleaser
Version: 2.0.2
Summary: Add-on for zest.releaser for releasing qgis plugins
Author-email: Reinout van Rees <reinout.vanrees@nelen-schuurmans.nl>
License-Expression: GPL-3.0-or-later
Requires-Python: >=3.10
License-File: LICENSE.rst
Requires-Dist: zest-releaser>=9
Dynamic: license-file
